{
  "version": "5.1.1",
  "flags": {},
  "shapes": [
    {
      "label": "sjb_rect",
      "points": [
        [
          1382.2580645161293,
          1259.6774193548388
        ],
        [
          2950.0,
          2311.2903225806454
        ]
      ],
      "group_id": null,
      "shape_type": "rectangle",
      "flags": {}
    },
    {
      "label": "angle_30",
      "points": [
        [
          2911.2903225806454,
          2277.4193548387093
        ]
      ],
      "group_id": null,
      "shape_type": "point",
      "flags": {}
    },
    {
      "label": "angle_60",
      "points": [
        [
          1420.967741935484,
          1809.6774193548388
        ]
      ],
      "group_id": null,
      "shape_type": "point",
      "flags": {}
    },
    {
      "label": "angle_90",
      "points": [
        [
          1959.677419354839,
          1287.0967741935483
        ]
      ],
      "group_id": null,
      "shape_type": "point",
      "flags": {}
    }
  ],
  "imagePath": "MVIMG_20230331_082232.jpg",
  "imageData": null,
  "imageHeight": 3000,
  "imageWidth": 4000
}